gspsa_gradients/__init__.py
gspsa_gradients/qiskit_gradient/__init__.py
gspsa_gradients/qiskit_gradient/gspsa.py
gspsa_gradients/tfq_gradient/__init__.py
gspsa_gradients/tfq_gradient/gspsa.py
gspsa_gradients-1.0.0.dist-info/LICENSE
gspsa_gradients-1.0.0.dist-info/METADATA
gspsa_gradients-1.0.0.dist-info/WHEEL
gspsa_gradients-1.0.0.dist-info/top_level.txt
gspsa_gradients-1.0.0.dist-info/RECORD
