Metadata-Version: 2.1
Name: gspsa-gradients
Version: 1.0.0
Summary: Implementation of Guided-SPSA
Author-email: Maniraman Periyasamy <maniraman.periyasamy@gmail.com>
Project-URL: Homepage, https://github.com/maniraman-periyasamy/gspsa-gradients
Project-URL: Issues, https://github.com/maniraman-periyasamy/gspsa-gradients/issues
Classifier: Programming Language :: Python :: 3
Classifier: License :: OSI Approved :: MIT License
Classifier: Operating System :: OS Independent
Requires-Python: >=3.9
License-File: LICENSE
Provides-Extra: qiskit
Requires-Dist: qiskit ; extra == 'qiskit'
Requires-Dist: qiskit-algorithms ; extra == 'qiskit'
Provides-Extra: tfq
Requires-Dist: tensorflow-quantum ; extra == 'tfq'
Requires-Dist: tensorflow ; extra == 'tfq'
